LICENSE
MANIFEST.in
README.md
setup.py
tap_shiphero/__init__.py
tap_shiphero/client.py
tap_shiphero/discover.py
tap_shiphero/sync.py
tap_shiphero.egg-info/PKG-INFO
tap_shiphero.egg-info/SOURCES.txt
tap_shiphero.egg-info/dependency_links.txt
tap_shiphero.egg-info/entry_points.txt
tap_shiphero.egg-info/requires.txt
tap_shiphero.egg-info/top_level.txt
tap_shiphero/schemas/orders.json
tap_shiphero/schemas/products.json
tap_shiphero/schemas/shipments.json
tap_shiphero/schemas/vendors.json