Metadata-Version: 1.1
Name: tap-shiphero
Version: 1.0.2
Summary: Singer.io tap for extracting Shiphero data
Home-page: http://singer.io
Author: Stitch
Author-email: UNKNOWN
License: UNKNOWN
Platform: UNKNOWN
Classifier: Programming Language :: Python :: 3 :: Only
